flask_fullstack/__init__.py
flask_fullstack/base/__init__.py
flask_fullstack/base/interfaces.py
flask_fullstack/base/mixins.py
flask_fullstack/core.py
flask_fullstack/restx/__init__.py
flask_fullstack/restx/controller.py
flask_fullstack/restx/marshals.py
flask_fullstack/restx/parsers.py
flask_fullstack/restx/testing.py
flask_fullstack/siox/__init__.py
flask_fullstack/siox/controller.py
flask_fullstack/siox/errors.py
flask_fullstack/siox/eventor.py
flask_fullstack/siox/events.py
flask_fullstack/siox/interfaces.py
flask_fullstack/siox/structures.py
flask_fullstack/siox/testing.py
flask_fullstack/utils/__init__.py
flask_fullstack/utils/columns.py
flask_fullstack/utils/dicts.py
flask_fullstack/utils/flask.py
flask_fullstack/utils/kebabs.py
flask_fullstack/utils/models.py
flask_fullstack/utils/named.py
flask_fullstack/utils/other.py
flask_fullstack/utils/pydantic.py
flask_fullstack/utils/pytest.py
flask_fullstack/utils/sqlalchemy.py
flask_fullstack-0.5.10.dist-info/METADATA
flask_fullstack-0.5.10.dist-info/WHEEL
flask_fullstack-0.5.10.dist-info/RECORD
