Metadata-Version: 2.1
Name: flask-fullstack
Version: 0.5.10
Summary: A utility package for projects using flask, sqlalchemy, socketio and pytest
Author: niqzart
Author-email: niqzart@gmail.com
Requires-Python: >=3.10,<4.0
Classifier: Programming Language :: Python :: 3
Classifier: Programming Language :: Python :: 3.10
Classifier: Programming Language :: Python :: 3.11
Requires-Dist: flask (>=2.2.0,<2.4.0)
Requires-Dist: flask-cors (>=3.0.10,<3.1.0)
Requires-Dist: flask-jwt-extended (>=4.5.2,<4.6.0)
Requires-Dist: flask-restx (>=1.0.3,<1.1.0)
Requires-Dist: flask-socketio (>=5.1.2,<5.4.0)
Requires-Dist: flask-sqlalchemy (>=3.0.3,<3.2.0)
Requires-Dist: pydantic (>=2.0,<3.0)
Requires-Dist: pydantic-marshals (>=0.2.1)
Requires-Dist: sqlalchemy (>=1.4.31,<3.0.0)
Requires-Dist: werkzeug (>=2.2.0,<2.4.0)
Requires-Dist: whoosh (>=2.7.4,<2.8.0)
Requires-Dist: whooshalchemy (>=0.3.1,<0.4.0)
Project-URL: github, https://github.com/niqzart/flask-fullstack
